pi_tester.py
pitester.py
Engine/TestEngine.py
Engine/__init__.py
Engine/config.py
Engine/dblib.py
Engine/ext.py
Engine/feedback.py
Engine/parser.py
Engine/pi_config.py
Engine/reporter.py
pitester-1.0.0.dist-info/DESCRIPTION.rst
pitester-1.0.0.dist-info/METADATA
pitester-1.0.0.dist-info/RECORD
pitester-1.0.0.dist-info/WHEEL
pitester-1.0.0.dist-info/entry_points.txt
pitester-1.0.0.dist-info/metadata.json
pitester-1.0.0.dist-info/top_level.txt
