Metadata-Version: 2.0
Name: pitester
Version: 1.0.0
Summary: Automation test framework
Home-page: https://github.com/dkentw/pi-tester
Author: Dken
Author-email: dken.tw@gmail.com
License: MIT
Keywords: automation test
Platform: UNKNOWN
Requires-Dist: docutils (>=0.3)
Requires-Dist: junit-xml (>=1.7)
